avidaq/__init__.py
avidaq/_io.py
avidaq/_live_view.py
avidaq/_mda.py
avidaq/_reader.py
avidaq/_right_panel.py
avidaq/_sample_data.py
avidaq/_types.py
avidaq/_utils.py
avidaq/_widget.py
avidaq/_writer.py
avidaq/napari.yaml
avidaq/_tests/__init__.py
avidaq/_tests/test_mda.py
avidaq/_tests/test_reader.py
avidaq/_tests/test_widget.py
avidaq/_tests/test_writer.py
avidaq/icons/Thumbs.db
avidaq/icons/fast-forward-down.png
avidaq/icons/fast-forward-left.png
avidaq/icons/fast-forward-right.png
avidaq/icons/fast-forward-up.png
avidaq/icons/play-down.png
avidaq/icons/play-left.png
avidaq/icons/play-right.png
avidaq/icons/play-up.png
avidaq-0.0.5.dist-info/LICENSE
avidaq-0.0.5.dist-info/METADATA
avidaq-0.0.5.dist-info/WHEEL
avidaq-0.0.5.dist-info/entry_points.txt
avidaq-0.0.5.dist-info/top_level.txt
avidaq-0.0.5.dist-info/RECORD
