Metadata-Version: 2.1
Name: avidaq
Version: 0.0.5
Summary: controls for napari and micromanger
Author: Riley M Shea
Author-email: RileyMShea@gmail.com
License: BSD-3-Clause
Classifier: Development Status :: 2 - Pre-Alpha
Classifier: Framework :: napari
Classifier: Intended Audience :: Developers
Classifier: License :: OSI Approved :: BSD License
Classifier: Operating System :: OS Independent
Classifier: Programming Language :: Python
Classifier: Programming Language :: Python :: 3
Classifier: Programming Language :: Python :: 3 :: Only
Classifier: Programming Language :: Python :: 3.8
Classifier: Programming Language :: Python :: 3.9
Classifier: Programming Language :: Python :: 3.10
Classifier: Topic :: Scientific/Engineering :: Image Processing
Classifier: Typing :: Typed
Requires-Python: >=3.8
License-File: LICENSE
Requires-Dist: magicgui
Requires-Dist: numpy
Requires-Dist: pycromanager
Requires-Dist: qtpy
Provides-Extra: build
Requires-Dist: twine ; extra == 'build'
Provides-Extra: testing
Requires-Dist: black ; extra == 'testing'
Requires-Dist: ipykernel ; extra == 'testing'
Requires-Dist: matplotlib ; extra == 'testing'
Requires-Dist: napari ; extra == 'testing'
Requires-Dist: pyqt5 ; extra == 'testing'
Requires-Dist: pyright ; extra == 'testing'
Requires-Dist: pytest ; extra == 'testing'
Requires-Dist: pytest-cov ; extra == 'testing'
Requires-Dist: pytest-qt ; extra == 'testing'
Requires-Dist: tox ; extra == 'testing'
Requires-Dist: yappi ; extra == 'testing'
